 {
    "formations" :
        {
        
        "Offense" :
            {
                "Base" : [
                    
                    {
                        "positionID"	: "WR1",
                        "players"	: [
                            
                            "d1e7b054-2722-4a10-9dad-687267489bd5",
                            
                            "c432c051-c7d3-424b-af1f-1a29118cbf7e",
                            
                            "8f108190-40d6-4088-b248-a68113cb7a76"
                            
                        ]
                        },
                    
                    {
                        "positionID"	: "LT",
                        "players"	: [
                            
                            "eb5c2e5f-606e-4f3d-8463-a18ed4f099b3",
                            
                            "2ddb7c33-286b-41a3-a798-8b7c98121fe0"
                            
                        ]
                        },
                    
                    {
                        "positionID"	: "LG",
                        "players"	: [
                            
                            "f7ed97f5-f482-4f8d-b799-6e57357a7b43",
                            
                            "0e063e7a-9633-48e5-b5d0-b0ab023c185f"
                            
                        ]
                        },
                    
                    {
                        "positionID"	: "C",
                        "players"	: [
                            
                            "dc234ddd-cb75-4c7c-b788-7b0ce466ac02",
                            
                            "25a125d1-7249-40d0-8e54-5216fc7632b9"
                            
                        ]
                        },
                    
                    {
                        "positionID"	: "RG",
                        "players"	: [
                            
                            "25a125d1-7249-40d0-8e54-5216fc7632b9",
                            
                            "15b36c49-3963-4068-917f-da2c81bb04fa"
                            
                        ]
                        },
                    
                    {
                        "positionID"	: "RT",
                        "players"	: [
                            
                            "8f9e803f-7753-4ce8-9e81-c2e0060d8a97",
                            
                            "1b4da73c-2653-4432-9402-e44501d9ae6a"
                            
                        ]
                        },
                    
                    {
                        "positionID"	: "TE",
                        "players"	: [
                            
                            "584951cd-5c09-4953-9d29-598cc0896a81",
                            
                            "f17f786c-81ad-4d08-9338-c8c2ed28db55"
                            
                        ]
                        },
                    
                    {
                        "positionID"	: "TE",
                        "players"	: [
                            
                            "928318af-6c12-4cb8-8c58-7e69a2736e42",
                            
                            "9f0d503b-2331-4cb7-a2fb-70e251876bda"
                            
                        ]
                        },
                    
                    {
                        "positionID"	: "WR2",
                        "players"	: [
                            
                            "28270fc7-9e37-47ff-b671-3e1d8dc41542",
                            
                            "06fdf559-8c14-402d-81f7-bcafc95c35dd",
                            
                            "ee50d6c8-d816-44a7-932f-3b91ac27b5d7"
                            
                        ]
                        },
                    
                    {
                        "positionID"	: "QB",
                        "players"	: [
                            
                            "9378c4ed-938c-434c-929d-4d45fe252101",
                            
                            "07bcb29c-9b5e-429d-b249-67c0c2cc63f7"
                            
                        ]
                        },
                    
                    {
                        "positionID"	: "RB",
                        "players"	: [
                            
                            "cc6121b7-c369-4013-b0ba-19079349f95c",
                            
                            "69ef7ebd-86c9-4f7f-831a-dda8c8bf1737",
                            
                            "f0f86744-4044-4f57-95b2-31e943d44e7b",
                            
                            "8dc73990-bf64-4358-8483-c447efa23aae"
                            
                        ]
                        }
                    
                    ]
              },

        
        "Defense" :
            {
                "Base" : [
                    
                    {
                        "positionID"	: "LDE",
                        "players"	: [
                            
                            "4a065377-8081-4dc1-a80f-daf22d74ba67",
                            
                            "37e12ff0-ac5c-4b49-ab93-2b890e4f3a10"
                            
                        ]
                        },
                    
                    {
                        "positionID"	: "NT",
                        "players"	: [
                            
                            "bf8cf00c-7670-4867-8311-7ce2ab422798",
                            
                            "7394af12-2914-477a-af09-c0194967fd16",
                            
                            "ef1116db-bf62-42f6-a27d-919c2955d1b3"
                            
                        ]
                        },
                    
                    {
                        "positionID"	: "DT",
                        "players"	: [
                            
                            "cce83be5-6849-488f-b8ed-cc876b47ca32",
                            
                            "ffcfe67f-8f23-4476-b783-72484d72cde0"
                            
                        ]
                        },
                    
                    {
                        "positionID"	: "RDE",
                        "players"	: [
                            
                            "b56aa7d9-808e-4cf2-a28c-ba03f25ef902",
                            
                            "3f5359d3-dee4-4ee9-a1ed-ce1606c80b22"
                            
                        ]
                        },
                    
                    {
                        "positionID"	: "SLB",
                        "players"	: [
                            
                            "9bebb34c-0623-4f5a-a496-47842ce24465",
                            
                            "2d021b2c-71ca-498b-b846-2c23775a6c87"
                            
                        ]
                        },
                    
                    {
                        "positionID"	: "MLB",
                        "players"	: [
                            
                            "5550e7d6-cb13-4ae1-8ae2-bb01fe4a7378",
                            
                            "e6c71663-2d97-43b9-b0f7-238763abb729"
                            
                        ]
                        },
                    
                    {
                        "positionID"	: "WLB",
                        "players"	: [
                            
                            "941b89df-2666-4d9f-810e-9b889ba417eb",
                            
                            "c57a5c87-3306-4910-80dd-298002ff0df8"
                            
                        ]
                        },
                    
                    {
                        "positionID"	: "LCB",
                        "players"	: [
                            
                            "3f89d93d-6289-497f-a912-0459ae1ab95e",
                            
                            "892e7752-8bcb-4be8-91ec-ae860dbbfceb"
                            
                        ]
                        },
                    
                    {
                        "positionID"	: "RCB",
                        "players"	: [
                            
                            "b0b37455-c97a-47ef-a771-06ea245efa49",
                            
                            "56b1cfba-be99-49e7-8629-6b105f791e73",
                            
                            "6a40fd6c-389a-4a6f-923b-8d65787d36f9"
                            
                        ]
                        },
                    
                    {
                        "positionID"	: "SS",
                        "players"	: [
                            
                            "b54424d2-1eec-4cea-b649-9973a8a8347d",
                            
                            "cbf7e95f-5682-4acb-8ed5-7e94f2003314",
                            
                            "c3adf4cc-90d0-44b1-9aa1-5d678749eae7"
                            
                        ]
                        },
                    
                    {
                        "positionID"	: "FS",
                        "players"	: [
                            
                            "5c3a8b35-39c1-4e2c-86e5-0e523ff89dc5",
                            
                            "6cc3b30c-6309-49b4-8eac-b1f0a3654cb4"
                            
                        ]
                        }
                    
                    ]
              },

        
        "Special Teams" :
            {
                "Base" : [
                    
                    {
                        "positionID"	: "P",
                        "players"	: [
                            
                            "1d34c7f7-455d-407c-9f66-9df83696a5da"
                            
                        ]
                        },
                    
                    {
                        "positionID"	: "KO",
                        "players"	: [
                            
                            "4a8d063a-e271-4496-b75d-ad49d1e777ee"
                            
                        ]
                        },
                    
                    {
                        "positionID"	: "LS",
                        "players"	: [
                            
                            "e5dda952-317e-4192-b234-2163bdf10f3c"
                            
                        ]
                        },
                    
                    {
                        "positionID"	: "H",
                        "players"	: [
                            
                            "1d34c7f7-455d-407c-9f66-9df83696a5da"
                            
                        ]
                        },
                    
                    {
                        "positionID"	: "PK",
                        "players"	: [
                            
                        ]
                        },
                    
                    {
                        "positionID"	: "PR",
                        "players"	: [
                            
                            "ee50d6c8-d816-44a7-932f-3b91ac27b5d7",
                            
                            "06fdf559-8c14-402d-81f7-bcafc95c35dd"
                            
                        ]
                        },
                    
                    {
                        "positionID"	: "KR",
                        "players"	: [
                            
                            "ee50d6c8-d816-44a7-932f-3b91ac27b5d7",
                            
                            "cc6121b7-c369-4013-b0ba-19079349f95c"
                            
                        ]
                        }
                    
                    ]
              }

        
        },
        "players" : [
          
              {
                    "id"	: "6a40fd6c-389a-4a6f-923b-8d65787d36f9",
                    "fname"	: "Tony",
                    "lname"	: "McRae",
                    "teamNumber"	:  "29",
                    "position"	: "CB",
                    "experience"	:  "1",
                    "age"	: "24",
                    "born"	: "05/03/93",
                    "hometown"	: "Laurinburg, N.C.",
                    "height"	: "5-10",
                    "weight"	: "185",
                    "college"	: "North Carolina A&T",
                    "image"	: "http://prod.static.bengals.clubs.nfl.com/",
			
					"moreDetailsButtonURL"	: "/team/roster/Tony-McRae/6a40fd6c-389a-4a6f-923b-8d65787d36f9"
              },
           
              {
                    "id"	: "5550e7d6-cb13-4ae1-8ae2-bb01fe4a7378",
                    "fname"	: "Vincent",
                    "lname"	: "Rey",
                    "teamNumber"	:  "57",
                    "position"	: "LB",
                    "experience"	:  "7",
                    "age"	: "30",
                    "born"	: "09/06/87",
                    "hometown"	: "Far Rockaway, NY",
                    "height"	: "6-0",
                    "weight"	: "250",
                    "college"	: "Duke",
                    "image"	: "http://prod.static.bengals.clubs.nfl.com/",
			
					"moreDetailsButtonURL"	: "/team/roster/Vincent-Rey/5550e7d6-cb13-4ae1-8ae2-bb01fe4a7378"
              },
           
              {
                    "id"	: "06fdf559-8c14-402d-81f7-bcafc95c35dd",
                    "fname"	: "Tyler",
                    "lname"	: "Boyd",
                    "teamNumber"	:  "83",
                    "position"	: "WR",
                    "experience"	:  "2",
                    "age"	: "23",
                    "born"	: "11/15/94",
                    "hometown"	: "Clairton, PA",
                    "height"	: "6-2",
                    "weight"	: "197",
                    "college"	: "Pittsburgh",
                    "image"	: "http://prod.static.bengals.clubs.nfl.com/",
			
					"moreDetailsButtonURL"	: "/team/roster/Tyler-Boyd/06fdf559-8c14-402d-81f7-bcafc95c35dd"
              },
           
              {
                    "id"	: "3f89d93d-6289-497f-a912-0459ae1ab95e",
                    "fname"	: "Dre",
                    "lname"	: "Kirkpatrick",
                    "teamNumber"	:  "27",
                    "position"	: "CB",
                    "experience"	:  "6",
                    "age"	: "28",
                    "born"	: "10/26/89",
                    "hometown"	: "Gadsden, AL",
                    "height"	: "6-2",
                    "weight"	: "185",
                    "college"	: "Alabama",
                    "image"	: "http://prod.static.bengals.clubs.nfl.com/",
			
					"moreDetailsButtonURL"	: "/team/roster/Dre-Kirkpatrick/3f89d93d-6289-497f-a912-0459ae1ab95e"
              },
           
              {
                    "id"	: "9378c4ed-938c-434c-929d-4d45fe252101",
                    "fname"	: "Andy",
                    "lname"	: "Dalton",
                    "teamNumber"	:  "14",
                    "position"	: "QB",
                    "experience"	:  "7",
                    "age"	: "30",
                    "born"	: "10/29/87",
                    "hometown"	: "Katy, TX",
                    "height"	: "6-2",
                    "weight"	: "220",
                    "college"	: "Texas Christian",
                    "image"	: "http://prod.static.bengals.clubs.nfl.com/",
			
					"moreDetailsButtonURL"	: "/team/roster/Andy-Dalton/9378c4ed-938c-434c-929d-4d45fe252101"
              },
           
              {
                    "id"	: "ffcfe67f-8f23-4476-b783-72484d72cde0",
                    "fname"	: "Ryan",
                    "lname"	: "Glasgow",
                    "teamNumber"	:  "98",
                    "position"	: "DT",
                    "experience"	:  "R",
                    "age"	: "24",
                    "born"	: "09/30/93",
                    "hometown"	: "Aurora, Ill.",
                    "height"	: "6-3",
                    "weight"	: "302",
                    "college"	: "Michigan",
                    "image"	: "http://prod.static.bengals.clubs.nfl.com/",
			
					"moreDetailsButtonURL"	: "/team/roster/Ryan-Glasgow/ffcfe67f-8f23-4476-b783-72484d72cde0"
              },
           
              {
                    "id"	: "25a125d1-7249-40d0-8e54-5216fc7632b9",
                    "fname"	: "Trey",
                    "lname"	: "Hopkins",
                    "teamNumber"	:  "66",
                    "position"	: "G/C",
                    "experience"	:  "2",
                    "age"	: "25",
                    "born"	: "07/06/92",
                    "hometown"	: "Houston, TX",
                    "height"	: "6-3",
                    "weight"	: "310",
                    "college"	: "Texas",
                    "image"	: "http://prod.static.bengals.clubs.nfl.com/",
			
					"moreDetailsButtonURL"	: "/team/roster/Trey-Hopkins/25a125d1-7249-40d0-8e54-5216fc7632b9"
              },
           
              {
                    "id"	: "f0f86744-4044-4f57-95b2-31e943d44e7b",
                    "fname"	: "Brian",
                    "lname"	: "Hill",
                    "teamNumber"	:  "23",
                    "position"	: "RB",
                    "experience"	:  "R",
                    "age"	: "22",
                    "born"	: "11/09/95",
                    "hometown"	: "Belleville, Ill.",
                    "height"	: "6-1",
                    "weight"	: "219",
                    "college"	: "Wyoming",
                    "image"	: "http://prod.static.bengals.clubs.nfl.com/",
			
					"moreDetailsButtonURL"	: "/team/roster/Brian-Hill/f0f86744-4044-4f57-95b2-31e943d44e7b"
              },
           
              {
                    "id"	: "b56aa7d9-808e-4cf2-a28c-ba03f25ef902",
                    "fname"	: "Michael",
                    "lname"	: "Johnson",
                    "teamNumber"	:  "90",
                    "position"	: "DE",
                    "experience"	:  "9",
                    "age"	: "31",
                    "born"	: "02/07/87",
                    "hometown"	: "Selma, AL",
                    "height"	: "6-7",
                    "weight"	: "272",
                    "college"	: "Georgia Tech",
                    "image"	: "http://prod.static.bengals.clubs.nfl.com/",
			
					"moreDetailsButtonURL"	: "/team/roster/Michael-Johnson/b56aa7d9-808e-4cf2-a28c-ba03f25ef902"
              },
           
              {
                    "id"	: "cce83be5-6849-488f-b8ed-cc876b47ca32",
                    "fname"	: "Geno",
                    "lname"	: "Atkins",
                    "teamNumber"	:  "97",
                    "position"	: "DT",
                    "experience"	:  "8",
                    "age"	: "30",
                    "born"	: "03/28/88",
                    "hometown"	: "Pembroke Pines, FL",
                    "height"	: "6-1",
                    "weight"	: "300",
                    "college"	: "Georgia",
                    "image"	: "http://prod.static.bengals.clubs.nfl.com/",
			
					"moreDetailsButtonURL"	: "/team/roster/Geno-Atkins/cce83be5-6849-488f-b8ed-cc876b47ca32"
              },
           
              {
                    "id"	: "892e7752-8bcb-4be8-91ec-ae860dbbfceb",
                    "fname"	: "Darqueze",
                    "lname"	: "Dennard",
                    "teamNumber"	:  "21",
                    "position"	: "CB",
                    "experience"	:  "4",
                    "age"	: "26",
                    "born"	: "10/10/91",
                    "hometown"	: "Dry Branch, GA",
                    "height"	: "5-11",
                    "weight"	: "198",
                    "college"	: "Michigan State ",
                    "image"	: "http://prod.static.bengals.clubs.nfl.com/",
			
					"moreDetailsButtonURL"	: "/team/roster/Darqueze-Dennard/892e7752-8bcb-4be8-91ec-ae860dbbfceb"
              },
           
              {
                    "id"	: "f7ed97f5-f482-4f8d-b799-6e57357a7b43",
                    "fname"	: "Clint",
                    "lname"	: "Boling",
                    "teamNumber"	:  "65",
                    "position"	: "G",
                    "experience"	:  "7",
                    "age"	: "28",
                    "born"	: "05/09/89",
                    "hometown"	: "Alpharetta, GA",
                    "height"	: "6-5",
                    "weight"	: "305",
                    "college"	: "Georgia",
                    "image"	: "http://prod.static.bengals.clubs.nfl.com/",
			
					"moreDetailsButtonURL"	: "/team/roster/Clint-Boling/f7ed97f5-f482-4f8d-b799-6e57357a7b43"
              },
           
              {
                    "id"	: "584951cd-5c09-4953-9d29-598cc0896a81",
                    "fname"	: "Tyler",
                    "lname"	: "Kroft",
                    "teamNumber"	:  "81",
                    "position"	: "TE",
                    "experience"	:  "3",
                    "age"	: "25",
                    "born"	: "10/15/92",
                    "hometown"	: "",
                    "height"	: "6-6",
                    "weight"	: "250",
                    "college"	: "Rutgers",
                    "image"	: "http://prod.static.bengals.clubs.nfl.com/",
			
					"moreDetailsButtonURL"	: "/team/roster/Tyler-Kroft/584951cd-5c09-4953-9d29-598cc0896a81"
              },
           
              {
                    "id"	: "69ef7ebd-86c9-4f7f-831a-dda8c8bf1737",
                    "fname"	: "Giovani",
                    "lname"	: "Bernard",
                    "teamNumber"	:  "25",
                    "position"	: "HB",
                    "experience"	:  "5",
                    "age"	: "26",
                    "born"	: "11/22/91",
                    "hometown"	: "Boca Raton, FL",
                    "height"	: "5-9",
                    "weight"	: "205",
                    "college"	: "North Carolina",
                    "image"	: "http://prod.static.bengals.clubs.nfl.com/",
			
					"moreDetailsButtonURL"	: "/team/roster/Giovani-Bernard/69ef7ebd-86c9-4f7f-831a-dda8c8bf1737"
              },
           
              {
                    "id"	: "f17f786c-81ad-4d08-9338-c8c2ed28db55",
                    "fname"	: "C.J.",
                    "lname"	: "Uzomah",
                    "teamNumber"	:  "87",
                    "position"	: "TE",
                    "experience"	:  "3",
                    "age"	: "25",
                    "born"	: "01/14/93",
                    "hometown"	: "Suwanee, GA",
                    "height"	: "6-6",
                    "weight"	: "265",
                    "college"	: "Auburn",
                    "image"	: "http://prod.static.bengals.clubs.nfl.com/",
			
					"moreDetailsButtonURL"	: "/team/roster/C.J.-Uzomah/f17f786c-81ad-4d08-9338-c8c2ed28db55"
              },
           
              {
                    "id"	: "d1e7b054-2722-4a10-9dad-687267489bd5",
                    "fname"	: "A.J.",
                    "lname"	: "Green",
                    "teamNumber"	:  "18",
                    "position"	: "WR",
                    "experience"	:  "7",
                    "age"	: "29",
                    "born"	: "07/31/88",
                    "hometown"	: "Summerville, SC",
                    "height"	: "6-4",
                    "weight"	: "210",
                    "college"	: "Georgia",
                    "image"	: "http://prod.static.bengals.clubs.nfl.com/",
			
					"moreDetailsButtonURL"	: "/team/roster/A.J.-Green/d1e7b054-2722-4a10-9dad-687267489bd5"
              },
           
              {
                    "id"	: "3f5359d3-dee4-4ee9-a1ed-ce1606c80b22",
                    "fname"	: "Jordan",
                    "lname"	: "Willis",
                    "teamNumber"	:  "75",
                    "position"	: "DE",
                    "experience"	:  "R",
                    "age"	: "22",
                    "born"	: "05/02/95",
                    "hometown"	: "San Diego, CA",
                    "height"	: "6-4",
                    "weight"	: "255",
                    "college"	: "Kansas State",
                    "image"	: "http://prod.static.bengals.clubs.nfl.com/",
			
					"moreDetailsButtonURL"	: "/team/roster/Jordan-Willis/3f5359d3-dee4-4ee9-a1ed-ce1606c80b22"
              },
           
              {
                    "id"	: "c3adf4cc-90d0-44b1-9aa1-5d678749eae7",
                    "fname"	: "Brandon",
                    "lname"	: "Wilson",
                    "teamNumber"	:  "40",
                    "position"	: "S",
                    "experience"	:  "R",
                    "age"	: "23",
                    "born"	: "07/27/94",
                    "hometown"	: "Shreveport, La.",
                    "height"	: "5-11",
                    "weight"	: "200",
                    "college"	: "Houston",
                    "image"	: "http://prod.static.bengals.clubs.nfl.com/",
			
					"moreDetailsButtonURL"	: "/team/roster/Brandon-Wilson/c3adf4cc-90d0-44b1-9aa1-5d678749eae7"
              },
           
              {
                    "id"	: "8f108190-40d6-4088-b248-a68113cb7a76",
                    "fname"	: "Josh",
                    "lname"	: "Malone",
                    "teamNumber"	:  "80",
                    "position"	: "WR",
                    "experience"	:  "R",
                    "age"	: "22",
                    "born"	: "03/21/96",
                    "hometown"	: "Gallatin, Tenn.",
                    "height"	: "6-3",
                    "weight"	: "208",
                    "college"	: "Tennessee",
                    "image"	: "http://prod.static.bengals.clubs.nfl.com/",
			
					"moreDetailsButtonURL"	: "/team/roster/Josh-Malone/8f108190-40d6-4088-b248-a68113cb7a76"
              },
           
              {
                    "id"	: "ee50d6c8-d816-44a7-932f-3b91ac27b5d7",
                    "fname"	: "Alex",
                    "lname"	: "Erickson",
                    "teamNumber"	:  "12",
                    "position"	: "WR",
                    "experience"	:  "2",
                    "age"	: "25",
                    "born"	: "11/06/92",
                    "hometown"	: "Darlington, Wis.",
                    "height"	: "6-0",
                    "weight"	: "195",
                    "college"	: "Wisconsin",
                    "image"	: "http://prod.static.bengals.clubs.nfl.com/",
			
					"moreDetailsButtonURL"	: "/team/roster/Alex-Erickson/ee50d6c8-d816-44a7-932f-3b91ac27b5d7"
              },
           
              {
                    "id"	: "b54424d2-1eec-4cea-b649-9973a8a8347d",
                    "fname"	: "Shawn",
                    "lname"	: "Williams",
                    "teamNumber"	:  "36",
                    "position"	: "S",
                    "experience"	:  "5",
                    "age"	: "26",
                    "born"	: "05/13/91",
                    "hometown"	: "Damascus, GA",
                    "height"	: "6-0",
                    "weight"	: "210",
                    "college"	: "Georgia",
                    "image"	: "http://prod.static.bengals.clubs.nfl.com/",
			
					"moreDetailsButtonURL"	: "/team/roster/Shawn-Williams/b54424d2-1eec-4cea-b649-9973a8a8347d"
              },
           
              {
                    "id"	: "b0b37455-c97a-47ef-a771-06ea245efa49",
                    "fname"	: "William",
                    "lname"	: "Jackson",
                    "teamNumber"	:  "22",
                    "position"	: "CB",
                    "experience"	:  "2",
                    "age"	: "25",
                    "born"	: "10/27/92",
                    "hometown"	: "",
                    "height"	: "6-0",
                    "weight"	: "187",
                    "college"	: "Houston",
                    "image"	: "http://prod.static.bengals.clubs.nfl.com/",
			
					"moreDetailsButtonURL"	: "/team/roster/William-Jackson/b0b37455-c97a-47ef-a771-06ea245efa49"
              },
           
              {
                    "id"	: "2ddb7c33-286b-41a3-a798-8b7c98121fe0",
                    "fname"	: "Justin",
                    "lname"	: "Murray",
                    "teamNumber"	:  "72",
                    "position"	: "OT",
                    "experience"	:  "1",
                    "age"	: "24",
                    "born"	: "04/19/93",
                    "hometown"	: "Cincinnati, Ohio",
                    "height"	: "6-5",
                    "weight"	: "304",
                    "college"	: "Cincinnati",
                    "image"	: "http://prod.static.bengals.clubs.nfl.com/",
			
					"moreDetailsButtonURL"	: "/team/roster/Justin-Murray/2ddb7c33-286b-41a3-a798-8b7c98121fe0"
              },
           
              {
                    "id"	: "7394af12-2914-477a-af09-c0194967fd16",
                    "fname"	: "Pat",
                    "lname"	: "Sims",
                    "teamNumber"	:  "92",
                    "position"	: "DT",
                    "experience"	:  "10",
                    "age"	: "32",
                    "born"	: "11/29/85",
                    "hometown"	: "Fort Lauderdale, FL",
                    "height"	: "6-2",
                    "weight"	: "330",
                    "college"	: "Auburn",
                    "image"	: "http://prod.static.bengals.clubs.nfl.com/",
			
					"moreDetailsButtonURL"	: "/team/roster/Pat-Sims/7394af12-2914-477a-af09-c0194967fd16"
              },
           
              {
                    "id"	: "928318af-6c12-4cb8-8c58-7e69a2736e42",
                    "fname"	: "Ryan",
                    "lname"	: "Hewitt",
                    "teamNumber"	:  "89",
                    "position"	: "H-B",
                    "experience"	:  "4",
                    "age"	: "27",
                    "born"	: "01/24/91",
                    "hometown"	: "Denver, CO",
                    "height"	: "6-4",
                    "weight"	: "255",
                    "college"	: "Stanford",
                    "image"	: "http://prod.static.bengals.clubs.nfl.com/",
			
					"moreDetailsButtonURL"	: "/team/roster/Ryan-Hewitt/928318af-6c12-4cb8-8c58-7e69a2736e42"
              },
           
              {
                    "id"	: "8f9e803f-7753-4ce8-9e81-c2e0060d8a97",
                    "fname"	: "Eric",
                    "lname"	: "Winston",
                    "teamNumber"	:  "73",
                    "position"	: "OT",
                    "experience"	:  "11",
                    "age"	: "34",
                    "born"	: "11/17/83",
                    "hometown"	: "Midland, TX",
                    "height"	: "6-7",
                    "weight"	: "310",
                    "college"	: "Miami (Fla.)",
                    "image"	: "http://prod.static.bengals.clubs.nfl.com/",
			
					"moreDetailsButtonURL"	: "/team/roster/Eric-Winston/8f9e803f-7753-4ce8-9e81-c2e0060d8a97"
              },
           
              {
                    "id"	: "e5dda952-317e-4192-b234-2163bdf10f3c",
                    "fname"	: "Clark",
                    "lname"	: "Harris",
                    "teamNumber"	:  "46",
                    "position"	: "LS",
                    "experience"	:  "9",
                    "age"	: "33",
                    "born"	: "07/10/84",
                    "hometown"	: "Manahawkin, NJ",
                    "height"	: "6-5",
                    "weight"	: "250",
                    "college"	: "Rutgers",
                    "image"	: "http://prod.static.bengals.clubs.nfl.com/",
			
					"moreDetailsButtonURL"	: "/team/roster/Clark-Harris/e5dda952-317e-4192-b234-2163bdf10f3c"
              },
           
              {
                    "id"	: "37e12ff0-ac5c-4b49-ab93-2b890e4f3a10",
                    "fname"	: "Chris",
                    "lname"	: "Smith",
                    "teamNumber"	:  "94",
                    "position"	: "DE",
                    "experience"	:  "4",
                    "age"	: "26",
                    "born"	: "02/11/92",
                    "hometown"	: "Mount Ulla, NC",
                    "height"	: "6-1",
                    "weight"	: "266",
                    "college"	: "Arkansas",
                    "image"	: "http://prod.static.bengals.clubs.nfl.com/",
			
					"moreDetailsButtonURL"	: "/team/roster/Chris-Smith/37e12ff0-ac5c-4b49-ab93-2b890e4f3a10"
              },
           
              {
                    "id"	: "ef1116db-bf62-42f6-a27d-919c2955d1b3",
                    "fname"	: "Josh",
                    "lname"	: "Tupou",
                    "teamNumber"	:  "68",
                    "position"	: "DT",
                    "experience"	:  "R",
                    "age"	: "23",
                    "born"	: "05/02/94",
                    "hometown"	: "Long Beach, CA.",
                    "height"	: "6-3",
                    "weight"	: "350",
                    "college"	: "Colorado",
                    "image"	: "http://prod.static.bengals.clubs.nfl.com/",
			
					"moreDetailsButtonURL"	: "/team/roster/Josh-Tupou/ef1116db-bf62-42f6-a27d-919c2955d1b3"
              },
           
              {
                    "id"	: "9f0d503b-2331-4cb7-a2fb-70e251876bda",
                    "fname"	: "Cethan",
                    "lname"	: "Carter",
                    "teamNumber"	:  "82",
                    "position"	: "H-B",
                    "experience"	:  "R",
                    "age"	: "24",
                    "born"	: "09/05/93",
                    "hometown"	: "",
                    "height"	: "6-3",
                    "weight"	: "241",
                    "college"	: "Nebraska",
                    "image"	: "http://prod.static.bengals.clubs.nfl.com/",
			
					"moreDetailsButtonURL"	: "/team/roster/Cethan-Carter/9f0d503b-2331-4cb7-a2fb-70e251876bda"
              },
           
              {
                    "id"	: "bf8cf00c-7670-4867-8311-7ce2ab422798",
                    "fname"	: "Andrew",
                    "lname"	: "Billings",
                    "teamNumber"	:  "99",
                    "position"	: "DT",
                    "experience"	:  "2",
                    "age"	: "23",
                    "born"	: "03/06/95",
                    "hometown"	: "Waco, TX",
                    "height"	: "6-1",
                    "weight"	: "325",
                    "college"	: "Baylor",
                    "image"	: "http://prod.static.bengals.clubs.nfl.com/",
			
					"moreDetailsButtonURL"	: "/team/roster/Andrew-Billings/bf8cf00c-7670-4867-8311-7ce2ab422798"
              },
           
              {
                    "id"	: "8dc73990-bf64-4358-8483-c447efa23aae",
                    "fname"	: "Jarveon",
                    "lname"	: "Williams",
                    "teamNumber"	:  "39",
                    "position"	: "RB",
                    "experience"	:  "R",
                    "age"	: "23",
                    "born"	: "01/03/95",
                    "hometown"	: "Converse, Texas",
                    "height"	: "5-9",
                    "weight"	: "205",
                    "college"	: "Texas-San Antonio",
                    "image"	: "http://prod.static.bengals.clubs.nfl.com/",
			
					"moreDetailsButtonURL"	: "/team/roster/Jarveon-Williams/8dc73990-bf64-4358-8483-c447efa23aae"
              },
           
              {
                    "id"	: "2d021b2c-71ca-498b-b846-2c23775a6c87",
                    "fname"	: "Carl",
                    "lname"	: "Lawson",
                    "teamNumber"	:  "58",
                    "position"	: "LB",
                    "experience"	:  "R",
                    "age"	: "22",
                    "born"	: "06/29/95",
                    "hometown"	: "Alpharetta, GA",
                    "height"	: "6-2",
                    "weight"	: "261",
                    "college"	: "Auburn",
                    "image"	: "http://prod.static.bengals.clubs.nfl.com/",
			
					"moreDetailsButtonURL"	: "/team/roster/Carl-Lawson/2d021b2c-71ca-498b-b846-2c23775a6c87"
              },
           
              {
                    "id"	: "28270fc7-9e37-47ff-b671-3e1d8dc41542",
                    "fname"	: "Brandon",
                    "lname"	: "LaFell",
                    "teamNumber"	:  "11",
                    "position"	: "WR",
                    "experience"	:  "8",
                    "age"	: "31",
                    "born"	: "11/04/86",
                    "hometown"	: "Houston, TX",
                    "height"	: "6-3",
                    "weight"	: "210",
                    "college"	: "Louisiana State",
                    "image"	: "http://prod.static.bengals.clubs.nfl.com/",
			
					"moreDetailsButtonURL"	: "/team/roster/Brandon-LaFell/28270fc7-9e37-47ff-b671-3e1d8dc41542"
              },
           
              {
                    "id"	: "15b36c49-3963-4068-917f-da2c81bb04fa",
                    "fname"	: "Alex",
                    "lname"	: "Redmond",
                    "teamNumber"	:  "62",
                    "position"	: "G",
                    "experience"	:  "1",
                    "age"	: "23",
                    "born"	: "01/18/95",
                    "hometown"	: "Cerritos, Calif.",
                    "height"	: "6-5",
                    "weight"	: "310",
                    "college"	: "UCLA",
                    "image"	: "http://prod.static.bengals.clubs.nfl.com/",
			
					"moreDetailsButtonURL"	: "/team/roster/Alex-Redmond/15b36c49-3963-4068-917f-da2c81bb04fa"
              },
           
              {
                    "id"	: "5c3a8b35-39c1-4e2c-86e5-0e523ff89dc5",
                    "fname"	: "George",
                    "lname"	: "Iloka",
                    "teamNumber"	:  "43",
                    "position"	: "S",
                    "experience"	:  "6",
                    "age"	: "28",
                    "born"	: "03/31/90",
                    "hometown"	: "Houston, TX",
                    "height"	: "6-4",
                    "weight"	: "225",
                    "college"	: "Boise State",
                    "image"	: "http://prod.static.bengals.clubs.nfl.com/",
			
					"moreDetailsButtonURL"	: "/team/roster/George-Iloka/5c3a8b35-39c1-4e2c-86e5-0e523ff89dc5"
              },
           
              {
                    "id"	: "56b1cfba-be99-49e7-8629-6b105f791e73",
                    "fname"	: "KeiVarae",
                    "lname"	: "Russell",
                    "teamNumber"	:  "20",
                    "position"	: "CB",
                    "experience"	:  "2",
                    "age"	: "24",
                    "born"	: "10/19/93",
                    "hometown"	: "Everett, WA",
                    "height"	: "5-11",
                    "weight"	: "196",
                    "college"	: "Notre Dame",
                    "image"	: "http://prod.static.bengals.clubs.nfl.com/",
			
					"moreDetailsButtonURL"	: "/team/roster/KeiVarae-Russell/56b1cfba-be99-49e7-8629-6b105f791e73"
              },
           
              {
                    "id"	: "4a8d063a-e271-4496-b75d-ad49d1e777ee",
                    "fname"	: "Randy",
                    "lname"	: "Bullock",
                    "teamNumber"	:  "4",
                    "position"	: "K",
                    "experience"	:  "6",
                    "age"	: "28",
                    "born"	: "12/16/89",
                    "hometown"	: "Klein, Texas",
                    "height"	: "5-9",
                    "weight"	: "206",
                    "college"	: "Texas A&M",
                    "image"	: "http://prod.static.bengals.clubs.nfl.com/",
			
					"moreDetailsButtonURL"	: "/team/roster/Randy-Bullock/4a8d063a-e271-4496-b75d-ad49d1e777ee"
              },
           
              {
                    "id"	: "c432c051-c7d3-424b-af1f-1a29118cbf7e",
                    "fname"	: "Cody",
                    "lname"	: "Core",
                    "teamNumber"	:  "16",
                    "position"	: "WR",
                    "experience"	:  "2",
                    "age"	: "23",
                    "born"	: "04/17/94",
                    "hometown"	: "",
                    "height"	: "6-3",
                    "weight"	: "210",
                    "college"	: "Mississippi",
                    "image"	: "http://prod.static.bengals.clubs.nfl.com/",
			
					"moreDetailsButtonURL"	: "/team/roster/Cody-Core/c432c051-c7d3-424b-af1f-1a29118cbf7e"
              },
           
              {
                    "id"	: "0e063e7a-9633-48e5-b5d0-b0ab023c185f",
                    "fname"	: "Christian",
                    "lname"	: "Westerman",
                    "teamNumber"	:  "63",
                    "position"	: "G",
                    "experience"	:  "2",
                    "age"	: "25",
                    "born"	: "02/23/93",
                    "hometown"	: "Chandler, AZ",
                    "height"	: "6-3",
                    "weight"	: "300",
                    "college"	: "Arizona State",
                    "image"	: "http://prod.static.bengals.clubs.nfl.com/",
			
					"moreDetailsButtonURL"	: "/team/roster/Christian-Westerman/0e063e7a-9633-48e5-b5d0-b0ab023c185f"
              },
           
              {
                    "id"	: "e6c71663-2d97-43b9-b0f7-238763abb729",
                    "fname"	: "Hardy",
                    "lname"	: "Nickerson",
                    "teamNumber"	:  "56",
                    "position"	: "LB",
                    "experience"	:  "R",
                    "age"	: "24",
                    "born"	: "01/05/94",
                    "hometown"	: "Oakland, Calif.",
                    "height"	: "6-0",
                    "weight"	: "232",
                    "college"	: "Illinois",
                    "image"	: "http://prod.static.bengals.clubs.nfl.com/",
			
					"moreDetailsButtonURL"	: "/team/roster/Hardy-Nickerson/e6c71663-2d97-43b9-b0f7-238763abb729"
              },
           
              {
                    "id"	: "941b89df-2666-4d9f-810e-9b889ba417eb",
                    "fname"	: "Vontaze",
                    "lname"	: "Burfict",
                    "teamNumber"	:  "55",
                    "position"	: "LB",
                    "experience"	:  "6",
                    "age"	: "27",
                    "born"	: "09/24/90",
                    "hometown"	: "Inglewood, Calif. ",
                    "height"	: "6-1",
                    "weight"	: "255",
                    "college"	: "Arizona State",
                    "image"	: "http://prod.static.bengals.clubs.nfl.com/",
			
					"moreDetailsButtonURL"	: "/team/roster/Vontaze-Burfict/941b89df-2666-4d9f-810e-9b889ba417eb"
              },
           
              {
                    "id"	: "1b4da73c-2653-4432-9402-e44501d9ae6a",
                    "fname"	: "Kent",
                    "lname"	: "Perkins",
                    "teamNumber"	:  "76",
                    "position"	: "OT",
                    "experience"	:  "R",
                    "age"	: "23",
                    "born"	: "11/19/94",
                    "hometown"	: "Dallas, TX",
                    "height"	: "6-5",
                    "weight"	: "320",
                    "college"	: "Texas",
                    "image"	: "http://prod.static.bengals.clubs.nfl.com/",
			
					"moreDetailsButtonURL"	: "/team/roster/Kent-Perkins/1b4da73c-2653-4432-9402-e44501d9ae6a"
              },
           
              {
                    "id"	: "cc6121b7-c369-4013-b0ba-19079349f95c",
                    "fname"	: "Joe",
                    "lname"	: "Mixon",
                    "teamNumber"	:  "28",
                    "position"	: "HB",
                    "experience"	:  "R",
                    "age"	: "21",
                    "born"	: "07/24/96",
                    "hometown"	: "Oakley, CA",
                    "height"	: "6-1",
                    "weight"	: "228",
                    "college"	: "Oklahoma",
                    "image"	: "http://prod.static.bengals.clubs.nfl.com/",
			
					"moreDetailsButtonURL"	: "/team/roster/Joe-Mixon/cc6121b7-c369-4013-b0ba-19079349f95c"
              },
           
              {
                    "id"	: "eb5c2e5f-606e-4f3d-8463-a18ed4f099b3",
                    "fname"	: "Cedric",
                    "lname"	: "Ogbuehi",
                    "teamNumber"	:  "70",
                    "position"	: "OT",
                    "experience"	:  "3",
                    "age"	: "25",
                    "born"	: "04/25/92",
                    "hometown"	: "Allen, TX",
                    "height"	: "6-5",
                    "weight"	: "310",
                    "college"	: "Texas A&M",
                    "image"	: "http://prod.static.bengals.clubs.nfl.com/",
			
					"moreDetailsButtonURL"	: "/team/roster/Cedric-Ogbuehi/eb5c2e5f-606e-4f3d-8463-a18ed4f099b3"
              },
           
              {
                    "id"	: "cbf7e95f-5682-4acb-8ed5-7e94f2003314",
                    "fname"	: "Clayton",
                    "lname"	: "Fejedelem",
                    "teamNumber"	:  "42",
                    "position"	: "S",
                    "experience"	:  "2",
                    "age"	: "24",
                    "born"	: "06/02/93",
                    "hometown"	: "",
                    "height"	: "6-0",
                    "weight"	: "205",
                    "college"	: "Illinois",
                    "image"	: "http://prod.static.bengals.clubs.nfl.com/",
			
					"moreDetailsButtonURL"	: "/team/roster/Clayton-Fejedelem/cbf7e95f-5682-4acb-8ed5-7e94f2003314"
              },
           
              {
                    "id"	: "6cc3b30c-6309-49b4-8eac-b1f0a3654cb4",
                    "fname"	: "Josh",
                    "lname"	: "Shaw",
                    "teamNumber"	:  "26",
                    "position"	: "CB",
                    "experience"	:  "3",
                    "age"	: "26",
                    "born"	: "03/27/92",
                    "hometown"	: "Palmdale, Calif.",
                    "height"	: "6-1",
                    "weight"	: "200",
                    "college"	: "Southern California",
                    "image"	: "http://prod.static.bengals.clubs.nfl.com/",
			
					"moreDetailsButtonURL"	: "/team/roster/Josh-Shaw/6cc3b30c-6309-49b4-8eac-b1f0a3654cb4"
              },
           
              {
                    "id"	: "9bebb34c-0623-4f5a-a496-47842ce24465",
                    "fname"	: "Jordan",
                    "lname"	: "Evans",
                    "teamNumber"	:  "50",
                    "position"	: "LB",
                    "experience"	:  "R",
                    "age"	: "23",
                    "born"	: "01/27/95",
                    "hometown"	: "",
                    "height"	: "6-2",
                    "weight"	: "233",
                    "college"	: "Oklahoma",
                    "image"	: "http://prod.static.bengals.clubs.nfl.com/",
			
					"moreDetailsButtonURL"	: "/team/roster/Jordan-Evans/9bebb34c-0623-4f5a-a496-47842ce24465"
              },
           
              {
                    "id"	: "dc234ddd-cb75-4c7c-b788-7b0ce466ac02",
                    "fname"	: "Russell",
                    "lname"	: "Bodine",
                    "teamNumber"	:  "61",
                    "position"	: "C",
                    "experience"	:  "4",
                    "age"	: "25",
                    "born"	: "06/30/92",
                    "hometown"	: "",
                    "height"	: "6-3",
                    "weight"	: "308",
                    "college"	: "North Carolina",
                    "image"	: "http://prod.static.bengals.clubs.nfl.com/",
			
					"moreDetailsButtonURL"	: "/team/roster/Russell-Bodine/dc234ddd-cb75-4c7c-b788-7b0ce466ac02"
              },
           
              {
                    "id"	: "4a065377-8081-4dc1-a80f-daf22d74ba67",
                    "fname"	: "Carlos",
                    "lname"	: "Dunlap",
                    "teamNumber"	:  "96",
                    "position"	: "DE",
                    "experience"	:  "8",
                    "age"	: "29",
                    "born"	: "02/28/89",
                    "hometown"	: "North Charleston, SC",
                    "height"	: "6-6",
                    "weight"	: "280",
                    "college"	: "Florida",
                    "image"	: "http://prod.static.bengals.clubs.nfl.com/",
			
					"moreDetailsButtonURL"	: "/team/roster/Carlos-Dunlap/4a065377-8081-4dc1-a80f-daf22d74ba67"
              },
           
              {
                    "id"	: "1d34c7f7-455d-407c-9f66-9df83696a5da",
                    "fname"	: "Kevin",
                    "lname"	: "Huber",
                    "teamNumber"	:  "10",
                    "position"	: "P",
                    "experience"	:  "9",
                    "age"	: "32",
                    "born"	: "07/16/85",
                    "hometown"	: "Cincinnati, OH",
                    "height"	: "6-1",
                    "weight"	: "211",
                    "college"	: "Cincinnati",
                    "image"	: "http://prod.static.bengals.clubs.nfl.com/",
			
					"moreDetailsButtonURL"	: "/team/roster/Kevin-Huber/1d34c7f7-455d-407c-9f66-9df83696a5da"
              },
           
              {
                    "id"	: "c57a5c87-3306-4910-80dd-298002ff0df8",
                    "fname"	: "Brandon",
                    "lname"	: "Bell",
                    "teamNumber"	:  "52",
                    "position"	: "LB",
                    "experience"	:  "R",
                    "age"	: "23",
                    "born"	: "01/09/95",
                    "hometown"	: "Mays Landing, NJ",
                    "height"	: "6-1",
                    "weight"	: "230",
                    "college"	: "Penn State",
                    "image"	: "http://prod.static.bengals.clubs.nfl.com/",
			
					"moreDetailsButtonURL"	: "/team/roster/Brandon-Bell/c57a5c87-3306-4910-80dd-298002ff0df8"
              },
           
              {
                    "id"	: "07bcb29c-9b5e-429d-b249-67c0c2cc63f7",
                    "fname"	: "AJ",
                    "lname"	: "McCarron",
                    "teamNumber"	:  "5",
                    "position"	: "QB",
                    "experience"	:  "5",
                    "age"	: "27",
                    "born"	: "09/13/90",
                    "hometown"	: "Mobile, AL",
                    "height"	: "6-3",
                    "weight"	: "220",
                    "college"	: "Alabama",
                    "image"	: "http://prod.static.bengals.clubs.nfl.com/",
			
					"moreDetailsButtonURL"	: "/team/roster/AJ-McCarron/07bcb29c-9b5e-429d-b249-67c0c2cc63f7"
              }
           
        ]
    }
